Workbook
Name Div_mensal: Planilha_Invest!$C$24
Name Investimento_mês: Planilha_Invest!$C$20
Name Patrimonio: Planilha_Invest!$C$23
Name qntd_anos: Planilha_Invest!$C$21
Name Rendimento_Carteira: Planilha_Invest!$C$15
Name Salário: Planilha_Invest!$C$14
Name tx_mensal: Planilha_Invest!$C$22

Sheet Planilha_Invest
B12: Configurações
B14: Salário | C14: 5000
B15: Rendimento de Carteira | C15: 0.009
B16: Sugestões de Investimento | C16: =C14*30% -> 1500
B18: INVESTIMENTO MENSAL
B20: Quanto investir por mês? | C20: 1260
B21: Por Quantos Anos? | C21: 5
B22: Taxa de Rendimento Mensal? | C22: 0.0108
B23: Patrimônio Acumulado? | C23: =FV(tx_mensal,qntd_anos*12,Investimento_mês*-1) -> 105593.06
B24: Dividendos Mensais | C24: =C23*$C$15 -> 950.33758
B25: 2
B26: 5
B28: Cenários
D29: Dividendo
B30: Quanto em 2 anos? | C30: =FV(tx_mensal,E30*12,Investimento_mês)*-1 -> 34310.888 | D30: =C30*Rendimento_Carteira -> 308.79799 | E30: 2
B31: Quanto em 5 anos? | C31: =FV(tx_mensal,E31*12,Investimento_mês)*-1 -> 105593.06 | D31: =C31*$C$15 -> 950.33758 | E31: 5
B32: Quanto em 10 anos? | C32: =FV(tx_mensal,E32*12,Investimento_mês)*-1 -> 306756.66 | D32: =C32*$C$15 -> 2760.8099 | E32: 10
B33: Quanto em 20 anos? | C33: =FV(tx_mensal,E33*12,Investimento_mês)*-1 -> 1420081.7 | D33: =C33*$C$15 -> 12780.736 | E33: 20
B34: Quanto em 30 anos? | C34: =FV(tx_mensal,E34*12,Investimento_mês)*-1 -> 5460720.1 | D34: =C34*$C$15 -> 49146.481 | E34: 30
B36: PERFIL | C36: Agressivo
B37: VALOR A SER INVESTIDO POR MÊS | C37: 200000
B39: TIPO DE FII | C39: PERCENTUAL SUGERIDO | D39: VALORES
B40: Papel | C40: =VLOOKUP($C$36&"-"&B40,'Banco Dados'!$B$1:$E$24,4,FALSE) -> 0.5 | D40: =$C$37*C40 -> 100000
B41: Tijolo | C41: =VLOOKUP($C$36&"-"&B41,'Banco Dados'!$B$1:$E$24,4,FALSE) -> 0.1 | D41: =$C$37*C41 -> 20000
B42: Híbridos | C42: =VLOOKUP($C$36&"-"&B42,'Banco Dados'!$B$1:$E$24,4,FALSE) -> 0.05 | D42: =$C$37*C42 -> 10000
B43: FOFs | C43: =VLOOKUP($C$36&"-"&B43,'Banco Dados'!$B$1:$E$24,4,FALSE) -> 0.05 | D43: =$C$37*C43 -> 10000
B44: Desenvolvimento | C44: =VLOOKUP($C$36&"-"&B44,'Banco Dados'!$B$1:$E$24,4,FALSE) -> 0.2 | D44: =$C$37*C44 -> 40000
B45: Hotelarias | C45: =VLOOKUP($C$36&"-"&B45,'Banco Dados'!$B$1:$E$24,4,FALSE) -> 0.1 | D45: =$C$37*C45 -> 20000
D46: =SUM(D40:D45) -> 200000

Sheet Banco Dados
B2: Chave | C2: Perfil | D2: Tipo de FII | E2: %
B3: =C3&"-"&D3 -> Conservador-Papel | C3: Conservador | D3: Papel | E3: 0.3
B4: =C4&"-"&D4 -> Conservador-Tijolo | C4: Conservador | D4: Tijolo | E4: 0.5 | G4: Moderado-Tijolo | H4: =VLOOKUP(G4,B2:E25,4,FALSE)*100 -> 35
B5: =C5&"-"&D5 -> Conservador-Híbridos | C5: Conservador | D5: Híbridos | E5: 0.1
B6: =C6&"-"&D6 -> Conservador-FOFs | C6: Conservador | D6: FOFs | E6: 0.1
B7: =C7&"-"&D7 -> Conservador-Desenvolvimento | C7: Conservador | D7: Desenvolvimento | E7: 0
B8: =C8&"-"&D8 -> Conservador-Hotelarias | C8: Conservador | D8: Hotelarias | E8: 0
B9: =C9&"-"&D9 -> Moderado-Papel | C9: Moderado | D9: Papel | E9: 0.32
B10: =C10&"-"&D10 -> Moderado-Tijolo | C10: Moderado | D10: Tijolo | E10: 0.35
B11: =C11&"-"&D11 -> Moderado-Híbridos | C11: Moderado | D11: Híbridos | E11: 0.08
B12: =C12&"-"&D12 -> Moderado-FOFs | C12: Moderado | D12: FOFs | E12: 0.05
B13: =C13&"-"&D13 -> Moderado-Desenvolvimento | C13: Moderado | D13: Desenvolvimento | E13: 0.1
B14: =C14&"-"&D14 -> Moderado-Hotelarias | C14: Moderado | D14: Hotelarias | E14: 0.1
B15: =C15&"-"&D15 -> Agressivo-Papel | C15: Agressivo | D15: Papel | E15: 0.5
B16: =C16&"-"&D16 -> Agressivo-Tijolo | C16: Agressivo | D16: Tijolo | E16: 0.1
... B20: =C20&"-"&D20 -> Agressivo-Hotelarias | C20: Agressivo | D20: Hotelarias | E20: 0.1
